laser_mind_client_meta/__init__.py
laser_mind_client_meta/laser_mind_message_keys.py
laser_mind_client_meta-0.12.0.dist-info/licenses/LICENSE
laser_mind_client_meta-0.12.0.dist-info/METADATA
laser_mind_client_meta-0.12.0.dist-info/WHEEL
laser_mind_client_meta-0.12.0.dist-info/top_level.txt
laser_mind_client_meta-0.12.0.dist-info/RECORD
