Metadata-Version: 2.4
Name: laser-mind-client-meta
Version: 0.12.0
Summary: A meta data package for laser mind clients
Author-email: Assaf Kalinski <assaf@lightsolver.com>
Project-URL: Homepage, https://lightsolver.com
Classifier: Programming Language :: Python :: 3
Classifier: License :: OSI Approved :: Apache Software License
Classifier: Operating System :: OS Independent
Requires-Python: >=3.8
License-File: LICENSE
Dynamic: license-file
